pixelsocial/__init__.py
pixelsocial/__main__.py
pixelsocial/_version.py
pixelsocial/api.py
pixelsocial/app.xdc
pixelsocial/cli.py
pixelsocial/feeds.py
pixelsocial/hooks.py
pixelsocial/migrations.py
pixelsocial/orm.py
pixelsocial/util.py
pixelsocial-0.15.0.dist-info/licenses/LICENSE
pixelsocial-0.15.0.dist-info/METADATA
pixelsocial-0.15.0.dist-info/WHEEL
pixelsocial-0.15.0.dist-info/entry_points.txt
pixelsocial-0.15.0.dist-info/top_level.txt
pixelsocial-0.15.0.dist-info/RECORD
